byutpl/__init__.py
byutpl/eos/__init__.py
byutpl/eos/pr.py
byutpl/eos/srk.py
byutpl/equations/__init__.py
byutpl/equations/dippreqns.py
byutpl/predictions/__init__.py
byutpl/predictions/predictions.py
byutpl/properties/__init__.py
byutpl/properties/air.py
byutpl/properties/benzene.py
byutpl/properties/water.py
byu_tpl-1.0.0.dist-info/LICENSE
byu_tpl-1.0.0.dist-info/METADATA
byu_tpl-1.0.0.dist-info/WHEEL
byu_tpl-1.0.0.dist-info/top_level.txt
byu_tpl-1.0.0.dist-info/RECORD
