Metadata-Version: 2.1
Name: byu-tpl
Version: 1.0.0
Summary: Brigham Young University Thermophysical Properties Laboratory
Home-page: http://knotts.byu.edu/
Author: Thomas Allen Knotts IV
Author-email: thomas.knotts@byu.edu
License: GPLv3
Download-URL: https://github.com/thomasknotts/byutpl/releases
Keywords: thermodynamics properties engineering
Platform: UNKNOWN
Classifier: Development Status :: 5 - Production/Stable
Classifier: Intended Audience :: Science/Research
Classifier: Intended Audience :: Education
Classifier: Intended Audience :: End Users/Desktop
Classifier: License :: OSI Approved :: GNU General Public License v3 (GPLv3)
Requires-Python: >=3.6
Requires-Dist: numpy
Requires-Dist: scipy
